readPdfFile/PDFReader.py
readPdfFile/__init__.py
readPdfFile/harshTest.py
readPdfFile-1.0.3.dist-info/METADATA
readPdfFile-1.0.3.dist-info/WHEEL
readPdfFile-1.0.3.dist-info/top_level.txt
readPdfFile-1.0.3.dist-info/RECORD
