Metadata-Version: 2.1
Name: readPdfFile
Version: 1.0.3
Summary: read pdf file
Author: Harsh Jani
Author-email: jani99harsh@gmail.com
Classifier: Programming Language :: Python :: 3
Classifier: License :: OSI Approved :: MIT License
Classifier: Operating System :: OS Independent
